pyfxtran/__init__.py
pyfxtran/_get_make_options.sh
pyfxtran/bin/fxtran
pyfxtran-0.1.5.dist-info/METADATA
pyfxtran-0.1.5.dist-info/WHEEL
pyfxtran-0.1.5.dist-info/entry_points.txt
pyfxtran-0.1.5.dist-info/top_level.txt
pyfxtran-0.1.5.dist-info/RECORD
pyfxtran-0.1.5.dist-info/licenses/LICENSE
