Metadata-Version: 2.4
Name: pyfxtran
Version: 0.1.5
Summary: A light wrapper around fxtran
Author-email: Sébastien Riette <sebastien.riette@meteo.fr>
License-Expression: CECILL-C
Requires-Python: >=3.8
License-File: LICENSE
Dynamic: license-file
